google_ai_studio_utils/config.py
google_ai_studio_utils/github_copilot_chat_conversation_json_to_html.py
google_ai_studio_utils/google_ai_studio_conversation_csv_to_html.py
google_ai_studio_utils/google_ai_studio_conversation_python_to_html.py
google_ai_studio_utils/metadata_utils.py
google_ai_studio_utils/python_conversation_to_html.py
google_ai_studio_utils/templates/google-ai-studio-conversation.html
google_ai_studio_utils/utils.py
google_ai_studio_utils-1.1.1.dist-info/METADATA
google_ai_studio_utils-1.1.1.dist-info/WHEEL
google_ai_studio_utils-1.1.1.dist-info/entry_points.txt
google_ai_studio_utils-1.1.1.dist-info/RECORD
